Metadata-Version: 1.0
Name: rkkpy
Version: 5.0
Summary: An example python package
Home-page: https://github.com/BillMills/python-package-example
Author: Test author
Author-email: myemail@example.com
License: MIT
Platform: UNKNOWN
